{
    "Slur": 0.0,
    "SlurFit": 0.0,
    "CritRate": 0.0,
    "CritRateFit": 0.0,
    "Power": 300.0,
    "Wince": 10.0,
    "Break": 10.0,
    "PowerRate": 1.0,
    "WinceRate": 1.0,
    "BreakRate": 1.0,
    "FitRatePower": 1.0,
    "FitRateWince": 1.0,
    "FitRateBreak": 1.0,
    "CritRatePower": 1.0,
    "CritRateWince": 1.0,
    "CritRateBreak": 1.0,
    "FireBulletType": 1,
    "HoldAddFocus": 0.0,
    "MoveSubFocus": -1000.0,
    "ShootSubFocus": 0.0,
    "WatchSubFocus": 0.0,
    "KeepFitLimitFocus": 100.0,
    "HitNum": 1.0,
    "HitNumBonusFit": 0.0,
    "HitNumBonusCrit": 0.0,
    "PerformanceValue": 0.0,
    "BulletSpeed": 400.0,
    "MaxRange": 20.0,
    "EffectiveRange": 10.0,
    "Gravity": 9.8,
    "RecoilHorizontalMin" : 0.0,
    "RecoilHorizontalMax" : 0.0,
    "RecoilVerticalMin" : 0.035,
    "RecoilVerticalMax" : 0.0,
    "PartsIndex": 16,
    "Capacity" : 7,
    "InfiniteAmmo": false
}
